flme/__init__.py
flme/lme_forecast_verbose.py
flme/rutils.py
flme/utils.py
flme/limetr/__init__.py
flme/limetr/utils.py
flme-0.1.1.dist-info/LICENSE
flme-0.1.1.dist-info/METADATA
flme-0.1.1.dist-info/WHEEL
flme-0.1.1.dist-info/top_level.txt
flme-0.1.1.dist-info/RECORD
