Metadata-Version: 2.1
Name: flme
Version: 0.1.1
Summary: Wrapper of limetr for FHS
Author-email: IHME Math Sciences <ihme.math.sciences@gmail.com>
License: BSD 2-Clause License
Project-URL: github, https://github.com/ihmeuw-msca/lme-for-forecast
License-File: LICENSE
Requires-Dist: numpy
Requires-Dist: scipy
Requires-Dist: spmat <0.1.0
Requires-Dist: xarray
Provides-Extra: test
Requires-Dist: pytest ; extra == 'test'
